.gitignore
INSTALL
LICENSE
README.md
requirements.txt
setup.py
C3PO.egg-info/PKG-INFO
C3PO.egg-info/SOURCES.txt
C3PO.egg-info/dependency_links.txt
C3PO.egg-info/entry_points.txt
C3PO.egg-info/requires.txt
C3PO.egg-info/top_level.txt
c3po/__init__.py
c3po/c3po_cmd.py
c3po/tests.py
c3po/conf/__init__.py
c3po/conf/settings_default.py
c3po/converters/__init__.py
c3po/converters/po_csv.py
c3po/converters/po_ods.py
c3po/converters/unicode.py
c3po/mod/__init__.py
c3po/mod/communicator.py
c3po/mod/initializer.py