Metadata-Version: 1.1
Name: C3PO
Version: 0.1.1
Summary: C3PO is Python module responsible for converting all .po files from locale directory into one .ods
